{
  "id": "aaf85645f7b3",
  "user": "admin",
  "created_at": "2026-07-06T12:16:50.018097+00:00",
  "updated_at": "2026-07-06T12:16:50.669870+00:00",
  "status": "ready",
  "message": "Completed 500 simulations.",
  "running": false,
  "simulations": 500,
  "seed": null,
  "team_a": {
    "name": "Anindo",
    "formation": "4-3-3",
    "lineup": [
      {
        "slot": "GK",
        "player": "Mike Maignan",
        "captain": false,
        "vice_captain": false
      },
      {
        "slot": "RB",
        "player": "Josip Stanišić",
        "captain": false,
        "vice_captain": false
      },
      {
        "slot": "CB1",
        "player": "Edmond Tapsoba",
        "captain": false,
        "vice_captain": false
      },
      {
        "slot": "CB2",
        "player": "Marc Cucurella",
        "captain": false,
        "vice_captain": false
      },
      {
        "slot": "LB",
        "player": "Dayot Upamecano",
        "captain": false,
        "vice_captain": false
      },
      {
        "slot": "DM",
        "player": "João Palhinha",
        "captain": false,
        "vice_captain": false
      },
      {
        "slot": "CM",
        "player": "Enzo Fernández",
        "captain": false,
        "vice_captain": false
      },
      {
        "slot": "AM",
        "player": "Luis Díaz",
        "captain": false,
        "vice_captain": false
      },
      {
        "slot": "RW",
        "player": "Cole Palmer",
        "captain": false,
        "vice_captain": false
      },
      {
        "slot": "ST",
        "player": "Gonzalo Higuaín",
        "captain": false,
        "vice_captain": false
      },
      {
        "slot": "LW",
        "player": "Matheus Cunha",
        "captain": false,
        "vice_captain": false
      }
    ],
    "bench": [
      "Declan Rice",
      "Pau Cubarsí",
      "Manuel Locatelli"
    ],
    "prime_player": "",
    "peak_season": {
      "player": "",
      "season": ""
    },
    "sheet_meta": {
      "source": "google_sheets",
      "player_count": 14,
      "budgets": [
        60.0,
        80.0,
        80.0,
        180.0,
        80.0,
        10.0,
        60.0,
        10.0,
        200.0,
        40.0,
        80.0,
        10.0,
        40.0,
        40.0
      ],
      "ready": true,
      "full_roster": [
        "Declan Rice",
        "Pau Cubarsí",
        "Marc Cucurella",
        "Dayot Upamecano",
        "Enzo Fernández",
        "João Palhinha",
        "Gonzalo Higuaín",
        "Mike Maignan",
        "Luis Díaz",
        "Josip Stanišić",
        "Cole Palmer",
        "Edmond Tapsoba",
        "Manuel Locatelli",
        "Matheus Cunha"
      ],
      "roster_players": [
        "Mike Maignan",
        "Josip Stanišić",
        "Edmond Tapsoba",
        "Marc Cucurella",
        "Dayot Upamecano",
        "João Palhinha",
        "Enzo Fernández",
        "Luis Díaz",
        "Cole Palmer",
        "Gonzalo Higuaín",
        "Matheus Cunha"
      ],
      "bench_players": [
        "Declan Rice",
        "Pau Cubarsí",
        "Manuel Locatelli"
      ],
      "squad_size": 14
    }
  },
  "team_b": {
    "name": "Chintu",
    "formation": "4-3-3",
    "lineup": [
      {
        "slot": "GK",
        "player": "Yassine Bounou",
        "captain": false,
        "vice_captain": false
      },
      {
        "slot": "RB",
        "player": "Djed Spence",
        "captain": false,
        "vice_captain": false
      },
      {
        "slot": "CB1",
        "player": "Sergio Ramos",
        "captain": false,
        "vice_captain": false
      },
      {
        "slot": "CB2",
        "player": "Maxence Lacroix",
        "captain": false,
        "vice_captain": false
      },
      {
        "slot": "LB",
        "player": "Malick Thiaw",
        "captain": false,
        "vice_captain": false
      },
      {
        "slot": "DM",
        "player": "Adam Wharton",
        "captain": false,
        "vice_captain": false
      },
      {
        "slot": "CM",
        "player": "Nicolò Barella",
        "captain": false,
        "vice_captain": false
      },
      {
        "slot": "AM",
        "player": "Bruno Fernandes",
        "captain": false,
        "vice_captain": false
      },
      {
        "slot": "RW",
        "player": "Mason Greenwood",
        "captain": false,
        "vice_captain": false
      },
      {
        "slot": "ST",
        "player": "Erling Haaland",
        "captain": false,
        "vice_captain": false
      },
      {
        "slot": "LW",
        "player": "Jérémy Doku",
        "captain": false,
        "vice_captain": false
      }
    ],
    "bench": [
      "Fernandinho",
      "Leandro Trossard",
      "Jordan Pickford"
    ],
    "prime_player": "",
    "peak_season": {
      "player": "",
      "season": ""
    },
    "sheet_meta": {
      "source": "google_sheets",
      "player_count": 14,
      "budgets": [
        500.0,
        80.0,
        20.0,
        10.0,
        100.0,
        30.0,
        160.0,
        10.0,
        10.0,
        10.0,
        30.0,
        10.0,
        10.0,
        10.0
      ],
      "ready": true,
      "full_roster": [
        "Erling Haaland",
        "Bruno Fernandes",
        "Sergio Ramos",
        "Yassine Bounou",
        "Fernandinho",
        "Jérémy Doku",
        "Nicolò Barella",
        "Mason Greenwood",
        "Djed Spence",
        "Leandro Trossard",
        "Malick Thiaw",
        "Jordan Pickford",
        "Adam Wharton",
        "Maxence Lacroix"
      ],
      "roster_players": [
        "Yassine Bounou",
        "Djed Spence",
        "Sergio Ramos",
        "Maxence Lacroix",
        "Malick Thiaw",
        "Adam Wharton",
        "Nicolò Barella",
        "Bruno Fernandes",
        "Mason Greenwood",
        "Erling Haaland",
        "Jérémy Doku"
      ],
      "bench_players": [
        "Fernandinho",
        "Leandro Trossard",
        "Jordan Pickford"
      ],
      "squad_size": 14
    }
  },
  "report": {
    "generated_at": "2026-07-06T12:16:50.666927+00:00",
    "engine_version": "slot-aware-v2",
    "matchup": {
      "home": {
        "name": "Anindo",
        "formation": "4-3-3",
        "lineup": [
          {
            "player": "Mike Maignan",
            "slot": "GK",
            "captain": false,
            "vice_captain": false
          },
          {
            "player": "Josip Stanišić",
            "slot": "RB",
            "captain": false,
            "vice_captain": false
          },
          {
            "player": "Edmond Tapsoba",
            "slot": "CB1",
            "captain": false,
            "vice_captain": false
          },
          {
            "player": "Marc Cucurella",
            "slot": "CB2",
            "captain": false,
            "vice_captain": false
          },
          {
            "player": "Dayot Upamecano",
            "slot": "LB",
            "captain": false,
            "vice_captain": false
          },
          {
            "player": "João Palhinha",
            "slot": "DM",
            "captain": false,
            "vice_captain": false
          },
          {
            "player": "Enzo Fernández",
            "slot": "CM",
            "captain": false,
            "vice_captain": false
          },
          {
            "player": "Luis Díaz",
            "slot": "AM",
            "captain": false,
            "vice_captain": false
          },
          {
            "player": "Cole Palmer",
            "slot": "RW",
            "captain": false,
            "vice_captain": false
          },
          {
            "player": "Gonzalo Higuaín",
            "slot": "ST",
            "captain": false,
            "vice_captain": false
          },
          {
            "player": "Matheus Cunha",
            "slot": "LW",
            "captain": false,
            "vice_captain": false
          }
        ]
      },
      "away": {
        "name": "Chintu",
        "formation": "4-3-3",
        "lineup": [
          {
            "player": "Yassine Bounou",
            "slot": "GK",
            "captain": false,
            "vice_captain": false
          },
          {
            "player": "Djed Spence",
            "slot": "RB",
            "captain": false,
            "vice_captain": false
          },
          {
            "player": "Sergio Ramos",
            "slot": "CB1",
            "captain": false,
            "vice_captain": false
          },
          {
            "player": "Maxence Lacroix",
            "slot": "CB2",
            "captain": false,
            "vice_captain": false
          },
          {
            "player": "Malick Thiaw",
            "slot": "LB",
            "captain": false,
            "vice_captain": false
          },
          {
            "player": "Adam Wharton",
            "slot": "DM",
            "captain": false,
            "vice_captain": false
          },
          {
            "player": "Nicolò Barella",
            "slot": "CM",
            "captain": false,
            "vice_captain": false
          },
          {
            "player": "Bruno Fernandes",
            "slot": "AM",
            "captain": false,
            "vice_captain": false
          },
          {
            "player": "Mason Greenwood",
            "slot": "RW",
            "captain": false,
            "vice_captain": false
          },
          {
            "player": "Erling Haaland",
            "slot": "ST",
            "captain": false,
            "vice_captain": false
          },
          {
            "player": "Jérémy Doku",
            "slot": "LW",
            "captain": false,
            "vice_captain": false
          }
        ]
      }
    },
    "profiles": {
      "home": {
        "extended": {
          "defensive_unit": 0.528,
          "possession_control": 0.701,
          "chance_creation": 0.46,
          "attacking_effectiveness": 0.788,
          "formation_fit": 0.754,
          "pressing_intensity": 0.492,
          "transition_threat": 0.508,
          "aerial_defence": 0.548,
          "units": {
            "attack": 0.899,
            "finishing": 0.82,
            "chance_creation": 1.0,
            "midfield": 0.249,
            "defence": 0.192,
            "midfield_defence": 0.129,
            "transition_risk": 0.242,
            "goalkeeper": 0.685,
            "overall": 0.489,
            "gk_confidence": 0.953,
            "gk_is_backup": false
          },
          "xga_suppression": 0.795,
          "xg_split": {
            "finishing": 2.34,
            "creation": 0.37,
            "total_raw": 2.71
          },
          "fwd_xg90": 0.51,
          "avg_pass_pct": 85.2,
          "formation_fit_players": [
            {
              "player": "Mike Maignan",
              "slot": "GK",
              "fit": 0.763,
              "position": "GK"
            },
            {
              "player": "Josip Stanišić",
              "slot": "RB",
              "fit": 0.602,
              "position": "CB"
            },
            {
              "player": "Edmond Tapsoba",
              "slot": "CB1",
              "fit": 0.792,
              "position": "CB"
            },
            {
              "player": "Marc Cucurella",
              "slot": "CB2",
              "fit": 0.793,
              "position": "CB"
            },
            {
              "player": "Dayot Upamecano",
              "slot": "LB",
              "fit": 0.616,
              "position": "CB"
            },
            {
              "player": "João Palhinha",
              "slot": "DM",
              "fit": 0.872,
              "position": "CM"
            },
            {
              "player": "Enzo Fernández",
              "slot": "CM",
              "fit": 0.884,
              "position": "CM"
            },
            {
              "player": "Luis Díaz",
              "slot": "AM",
              "fit": 0.875,
              "position": "CM"
            },
            {
              "player": "Cole Palmer",
              "slot": "RW",
              "fit": 0.567,
              "position": "CM"
            },
            {
              "player": "Gonzalo Higuaín",
              "slot": "ST",
              "fit": 0.964,
              "position": "ST"
            },
            {
              "player": "Matheus Cunha",
              "slot": "LW",
              "fit": 0.566,
              "position": "ST"
            }
          ]
        },
        "fullbacks": {
          "fullbacks": [
            {
              "player": "Josip Stanišić",
              "slot": "RB",
              "xa90": 0.24,
              "key_passes90": 1.16,
              "creation_score": 0.372,
              "attack_exposure": 0.304,
              "fit": 0.602
            },
            {
              "player": "Dayot Upamecano",
              "slot": "LB",
              "xa90": 0.07,
              "key_passes90": 0.45,
              "creation_score": 0.191,
              "attack_exposure": 0.183,
              "fit": 0.616
            }
          ],
          "transition_risk": 0.242,
          "xga_suppression_base": 0.782,
          "xga_suppression_with_transition": 0.795
        },
        "trophy_multiplier": 1.0204,
        "players": [
          {
            "player": "Mike Maignan",
            "slot": "GK",
            "team": "AC Milan",
            "xg90": 0.0,
            "npxg90": 0.0,
            "xa90": 0.0,
            "xg_buildup90": 0.18,
            "rating": 7.16,
            "minutes": 3295,
            "trophy_bonus": 0.0,
            "trophy_notes": [
              "No title/finalist club in window"
            ]
          },
          {
            "player": "Josip Stanišić",
            "slot": "RB",
            "team": "FC Bayern München",
            "xg90": 0.07,
            "npxg90": 0.06,
            "xa90": 0.24,
            "xg_buildup90": 0.71,
            "rating": 6.91,
            "minutes": 1855,
            "trophy_bonus": 0.045,
            "trophy_notes": [
              "2025-2026: league winner (FC Bayern München)"
            ]
          },
          {
            "player": "Edmond Tapsoba",
            "slot": "CB1",
            "team": "Bayer 04 Leverkusen",
            "xg90": 0.06,
            "npxg90": 0.09,
            "xa90": 0.05,
            "xg_buildup90": 0.42,
            "rating": 7.04,
            "minutes": 2543,
            "trophy_bonus": 0.0,
            "trophy_notes": [
              "No title/finalist club in window"
            ]
          },
          {
            "player": "Marc Cucurella",
            "slot": "CB2",
            "team": "Chelsea",
            "xg90": 0.08,
            "npxg90": 0.08,
            "xa90": 0.09,
            "xg_buildup90": 0.38,
            "rating": 6.86,
            "minutes": 2850,
            "trophy_bonus": 0.0,
            "trophy_notes": [
              "No title/finalist club in window"
            ]
          },
          {
            "player": "Dayot Upamecano",
            "slot": "LB",
            "team": "FC Bayern München",
            "xg90": 0.06,
            "npxg90": 0.07,
            "xa90": 0.07,
            "xg_buildup90": 0.72,
            "rating": 7.27,
            "minutes": 1779,
            "trophy_bonus": 0.0889,
            "trophy_notes": [
              "2024-2025: league winner (FC Bayern München)",
              "2025-2026: league winner (FC Bayern München)"
            ]
          },
          {
            "player": "João Palhinha",
            "slot": "DM",
            "team": "Tottenham Hotspur",
            "xg90": 0.11,
            "npxg90": 0.14,
            "xa90": 0.03,
            "xg_buildup90": 0.14,
            "rating": 7.02,
            "minutes": 2197,
            "trophy_bonus": 0.0,
            "trophy_notes": [
              "No title/finalist club in window"
            ]
          },
          {
            "player": "Enzo Fernández",
            "slot": "CM",
            "team": "Chelsea",
            "xg90": 0.26,
            "npxg90": 0.24,
            "xa90": 0.2,
            "xg_buildup90": 0.4,
            "rating": 7.23,
            "minutes": 3033,
            "trophy_bonus": 0.0,
            "trophy_notes": [
              "No title/finalist club in window"
            ]
          },
          {
            "player": "Luis Díaz",
            "slot": "AM",
            "team": "FC Bayern München",
            "xg90": 0.5,
            "npxg90": 0.54,
            "xa90": 0.23,
            "xg_buildup90": 0.56,
            "rating": 7.25,
            "minutes": 2430,
            "trophy_bonus": 0.09,
            "trophy_notes": [
              "2024-2025: league winner (Liverpool FC)",
              "2025-2026: league winner (FC Bayern München)"
            ]
          },
          {
            "player": "Cole Palmer",
            "slot": "RW",
            "team": "Chelsea",
            "xg90": 0.49,
            "npxg90": 0.29,
            "xa90": 0.19,
            "xg_buildup90": 0.37,
            "rating": 7.33,
            "minutes": 2580,
            "trophy_bonus": 0.0,
            "trophy_notes": [
              "No title/finalist club in window"
            ]
          },
          {
            "player": "Gonzalo Higuaín",
            "slot": "ST",
            "team": "SSC Napoli",
            "xg90": 0.75,
            "npxg90": 0.75,
            "xa90": 0.0,
            "xg_buildup90": 0.16,
            "rating": 7.69,
            "minutes": 2989,
            "trophy_bonus": 0.0,
            "trophy_notes": [
              "No title/finalist club in window"
            ]
          },
          {
            "player": "Matheus Cunha",
            "slot": "LW",
            "team": "Manchester United",
            "xg90": 0.28,
            "npxg90": 0.25,
            "xa90": 0.15,
            "xg_buildup90": 0.36,
            "rating": 7.35,
            "minutes": 2551,
            "trophy_bonus": 0.0,
            "trophy_notes": [
              "No title/finalist club in window"
            ]
          }
        ]
      },
      "away": {
        "extended": {
          "defensive_unit": 0.525,
          "possession_control": 0.509,
          "chance_creation": 0.47,
          "attacking_effectiveness": 0.815,
          "formation_fit": 0.745,
          "pressing_intensity": 0.461,
          "transition_threat": 0.64,
          "aerial_defence": 0.628,
          "units": {
            "attack": 0.845,
            "finishing": 0.724,
            "chance_creation": 1.0,
            "midfield": 0.243,
            "defence": 0.187,
            "midfield_defence": 0.119,
            "transition_risk": 0.151,
            "goalkeeper": 0.334,
            "overall": 0.425,
            "gk_confidence": 0.82,
            "gk_is_backup": false
          },
          "xga_suppression": 0.844,
          "xg_split": {
            "finishing": 2.17,
            "creation": 0.37,
            "total_raw": 2.54
          },
          "fwd_xg90": 0.64,
          "avg_pass_pct": 74.9,
          "formation_fit_players": [
            {
              "player": "Yassine Bounou",
              "slot": "GK",
              "fit": 0.693,
              "position": "GK"
            },
            {
              "player": "Djed Spence",
              "slot": "RB",
              "fit": 0.576,
              "position": "CB"
            },
            {
              "player": "Sergio Ramos",
              "slot": "CB1",
              "fit": 0.723,
              "position": "CB"
            },
            {
              "player": "Maxence Lacroix",
              "slot": "CB2",
              "fit": 0.891,
              "position": "CB"
            },
            {
              "player": "Malick Thiaw",
              "slot": "LB",
              "fit": 0.556,
              "position": "CB"
            },
            {
              "player": "Adam Wharton",
              "slot": "DM",
              "fit": 0.812,
              "position": "CM"
            },
            {
              "player": "Nicolò Barella",
              "slot": "CM",
              "fit": 0.899,
              "position": "CM"
            },
            {
              "player": "Bruno Fernandes",
              "slot": "AM",
              "fit": 0.859,
              "position": "CM"
            },
            {
              "player": "Mason Greenwood",
              "slot": "RW",
              "fit": 0.605,
              "position": "ST"
            },
            {
              "player": "Erling Haaland",
              "slot": "ST",
              "fit": 0.928,
              "position": "ST"
            },
            {
              "player": "Jérémy Doku",
              "slot": "LW",
              "fit": 0.653,
              "position": "CM"
            }
          ]
        },
        "fullbacks": {
          "fullbacks": [
            {
              "player": "Djed Spence",
              "slot": "RB",
              "xa90": 0.07,
              "key_passes90": 0.49,
              "creation_score": 0.142,
              "attack_exposure": 0.164,
              "fit": 0.576
            },
            {
              "player": "Malick Thiaw",
              "slot": "LB",
              "xa90": 0.02,
              "key_passes90": 0.19,
              "creation_score": 0.069,
              "attack_exposure": 0.076,
              "fit": 0.556
            }
          ],
          "transition_risk": 0.151,
          "xga_suppression_base": 0.837,
          "xga_suppression_with_transition": 0.844
        },
        "trophy_multiplier": 1.0064,
        "players": [
          {
            "player": "Yassine Bounou",
            "slot": "GK",
            "team": "Al-Hilal",
            "xg90": 0.0,
            "npxg90": 0.0,
            "xa90": 0.0,
            "xg_buildup90": 0.0,
            "rating": 6.87,
            "minutes": 2565,
            "trophy_bonus": 0.0,
            "trophy_notes": [
              "No title/finalist club in window"
            ]
          },
          {
            "player": "Djed Spence",
            "slot": "RB",
            "team": "Tottenham Hotspur",
            "xg90": 0.03,
            "npxg90": 0.04,
            "xa90": 0.07,
            "xg_buildup90": 0.22,
            "rating": 6.72,
            "minutes": 1942,
            "trophy_bonus": 0.0,
            "trophy_notes": [
              "No title/finalist club in window"
            ]
          },
          {
            "player": "Sergio Ramos",
            "slot": "CB1",
            "team": "Real Madrid",
            "xg90": 0.18,
            "npxg90": 0.18,
            "xa90": 0.0,
            "xg_buildup90": 0.33,
            "rating": 6.82,
            "minutes": 3013,
            "trophy_bonus": 0.0,
            "trophy_notes": [
              "No title/finalist club in window"
            ]
          },
          {
            "player": "Maxence Lacroix",
            "slot": "CB2",
            "team": "Crystal Palace",
            "xg90": 0.08,
            "npxg90": 0.08,
            "xa90": 0.03,
            "xg_buildup90": 0.25,
            "rating": 6.96,
            "minutes": 3102,
            "trophy_bonus": 0.0,
            "trophy_notes": [
              "No title/finalist club in window"
            ]
          },
          {
            "player": "Malick Thiaw",
            "slot": "LB",
            "team": "Newcastle United",
            "xg90": 0.09,
            "npxg90": 0.18,
            "xa90": 0.02,
            "xg_buildup90": 0.26,
            "rating": 6.98,
            "minutes": 2383,
            "trophy_bonus": 0.0,
            "trophy_notes": [
              "No title/finalist club in window"
            ]
          },
          {
            "player": "Adam Wharton",
            "slot": "DM",
            "team": "Crystal Palace",
            "xg90": 0.05,
            "npxg90": 0.03,
            "xa90": 0.26,
            "xg_buildup90": 0.36,
            "rating": 7.06,
            "minutes": 2562,
            "trophy_bonus": 0.0,
            "trophy_notes": [
              "No title/finalist club in window"
            ]
          },
          {
            "player": "Nicolò Barella",
            "slot": "CM",
            "team": "Inter",
            "xg90": 0.09,
            "npxg90": 0.1,
            "xa90": 0.21,
            "xg_buildup90": 0.42,
            "rating": 7.19,
            "minutes": 2529,
            "trophy_bonus": 0.07,
            "trophy_notes": [
              "2024-2025: UCL finalist (Inter)",
              "2025-2026: league winner (Inter)"
            ]
          },
          {
            "player": "Bruno Fernandes",
            "slot": "AM",
            "team": "Manchester United",
            "xg90": 0.31,
            "npxg90": 0.22,
            "xa90": 0.3,
            "xg_buildup90": 0.37,
            "rating": 7.62,
            "minutes": 3045,
            "trophy_bonus": 0.0,
            "trophy_notes": [
              "No title/finalist club in window"
            ]
          },
          {
            "player": "Mason Greenwood",
            "slot": "RW",
            "team": "Olympique de Marseille",
            "xg90": 0.52,
            "npxg90": 0.34,
            "xa90": 0.23,
            "xg_buildup90": 0.4,
            "rating": 7.46,
            "minutes": 2641,
            "trophy_bonus": 0.0,
            "trophy_notes": [
              "No title/finalist club in window"
            ]
          },
          {
            "player": "Erling Haaland",
            "slot": "ST",
            "team": "Manchester City",
            "xg90": 0.75,
            "npxg90": 0.73,
            "xa90": 0.08,
            "xg_buildup90": 0.14,
            "rating": 7.29,
            "minutes": 2849,
            "trophy_bonus": 0.0,
            "trophy_notes": [
              "No title/finalist club in window"
            ]
          },
          {
            "player": "Jérémy Doku",
            "slot": "LW",
            "team": "Manchester City",
            "xg90": 0.11,
            "npxg90": 0.16,
            "xa90": 0.27,
            "xg_buildup90": 0.41,
            "rating": 7.34,
            "minutes": 1658,
            "trophy_bonus": 0.0,
            "trophy_notes": [
              "No title/finalist club in window"
            ]
          }
        ]
      }
    },
    "mechanics": {
      "home_attacks_vs_away_defence": 0.844,
      "away_attacks_vs_home_defence": 0.795,
      "midfield_battle": {
        "home_multiplier": 1.001,
        "away_multiplier": 0.999
      }
    },
    "monte_carlo": {
      "simulations": 500,
      "expected_xg": {
        "home": 2.25,
        "away": 1.96
      },
      "home_win_pct": 42.2,
      "draw_pct": 20.6,
      "away_win_pct": 37.2,
      "home_goals_avg": 2.09,
      "away_goals_avg": 1.92,
      "total_goals_avg": 4.01,
      "btts_pct": 74.2,
      "over_2_5_pct": 76.6,
      "scorelines": [
        {
          "score": "2-2",
          "pct": 7.6
        },
        {
          "score": "1-1",
          "pct": 7.6
        },
        {
          "score": "1-2",
          "pct": 7.4
        },
        {
          "score": "2-1",
          "pct": 6.6
        },
        {
          "score": "3-1",
          "pct": 5.6
        },
        {
          "score": "3-2",
          "pct": 5.6
        },
        {
          "score": "2-3",
          "pct": 5.0
        },
        {
          "score": "1-3",
          "pct": 4.6
        }
      ],
      "unit_ratings": {
        "home": {
          "attack": 0.917,
          "finishing": 0.837,
          "chance_creation": 1.0,
          "midfield": 0.257,
          "defence": 0.199,
          "midfield_defence": 0.134,
          "transition_risk": 0.242,
          "goalkeeper": 0.704,
          "overall": 0.502,
          "gk_confidence": 0.953,
          "gk_is_backup": false
        },
        "away": {
          "attack": 0.85,
          "finishing": 0.729,
          "chance_creation": 1.0,
          "midfield": 0.249,
          "defence": 0.191,
          "midfield_defence": 0.122,
          "transition_risk": 0.151,
          "goalkeeper": 0.339,
          "overall": 0.431,
          "gk_confidence": 0.82,
          "gk_is_backup": false
        }
      },
      "home_trophy_multiplier": 1.0204,
      "away_trophy_multiplier": 1.0064,
      "midfield_battle": {
        "home_chance_multiplier": 1.001,
        "away_chance_multiplier": 0.999
      },
      "bench_impact": {
        "home": {
          "bench_count": 3,
          "bench_players": [
            "Declan Rice",
            "Pau Cubarsí",
            "Manuel Locatelli"
          ],
          "starting_xi": [
            "Mike Maignan",
            "Josip Stanišić",
            "Edmond Tapsoba",
            "Marc Cucurella",
            "Dayot Upamecano",
            "João Palhinha",
            "Enzo Fernández",
            "Luis Díaz",
            "Cole Palmer",
            "Gonzalo Higuaín",
            "Matheus Cunha"
          ],
          "full_squad_size": 14,
          "players": [
            {
              "player": "Declan Rice",
              "fpl_position": "MID",
              "scores": {
                "attacking": 0.195,
                "creative": 0.545,
                "defensive": 0.352
              },
              "traits": {
                "xg90": 0.102,
                "npxg90": 0.111,
                "goals90": 0.122,
                "shots90": 1.343,
                "xa90": 0.19,
                "key_passes90": 1.898,
                "xg_buildup90": 0.351,
                "big_chances_created90": 0.501,
                "tackles90": 1.858,
                "interceptions90": 0.934,
                "clearances90": 1.927,
                "goals_prevented90": 0.0
              },
              "outstanding": {
                "attacking": false,
                "creative": false,
                "defensive": false
              }
            },
            {
              "player": "Pau Cubarsí",
              "fpl_position": "DEF",
              "scores": {
                "attacking": 0.039,
                "creative": 0.302,
                "defensive": 0.366
              },
              "traits": {
                "xg90": 0.023,
                "npxg90": 0.025,
                "goals90": 0.017,
                "shots90": 0.304,
                "xa90": 0.028,
                "key_passes90": 0.238,
                "xg_buildup90": 0.604,
                "big_chances_created90": 0.068,
                "tackles90": 1.282,
                "interceptions90": 0.773,
                "clearances90": 3.92,
                "goals_prevented90": 0.0
              },
              "outstanding": {
                "attacking": false,
                "creative": true,
                "defensive": false
              }
            },
            {
              "player": "Manuel Locatelli",
              "fpl_position": "MID",
              "scores": {
                "attacking": 0.114,
                "creative": 0.424,
                "defensive": 0.437
              },
              "traits": {
                "xg90": 0.071,
                "npxg90": 0.04,
                "goals90": 0.047,
                "shots90": 1.085,
                "xa90": 0.119,
                "key_passes90": 1.164,
                "xg_buildup90": 0.472,
                "big_chances_created90": 0.138,
                "tackles90": 2.669,
                "interceptions90": 0.949,
                "clearances90": 2.264,
                "goals_prevented90": 0.0
              },
              "outstanding": {
                "attacking": false,
                "creative": true,
                "defensive": true
              }
            }
          ],
          "boosts": {
            "attack": 0.0,
            "creation": 0.0109,
            "defence": 0.0131,
            "total_applied_pct": 0.024
          },
          "contributed": true,
          "summary": "3 on bench; 2 with standout quality (+2.4% squad depth boost).",
          "team": "Anindo"
        },
        "away": {
          "bench_count": 3,
          "bench_players": [
            "Fernandinho",
            "Leandro Trossard",
            "Jordan Pickford"
          ],
          "starting_xi": [
            "Yassine Bounou",
            "Djed Spence",
            "Sergio Ramos",
            "Maxence Lacroix",
            "Malick Thiaw",
            "Adam Wharton",
            "Nicolò Barella",
            "Bruno Fernandes",
            "Mason Greenwood",
            "Erling Haaland",
            "Jérémy Doku"
          ],
          "full_squad_size": 14,
          "players": [
            {
              "player": "Fernandinho",
              "fpl_position": "MID",
              "scores": {
                "attacking": 0.2,
                "creative": 0.295,
                "defensive": 0.282
              },
              "traits": {
                "xg90": 0.077,
                "npxg90": 0.077,
                "goals90": 0.16,
                "shots90": 1.5,
                "xa90": 0.089,
                "key_passes90": 0.0,
                "xg_buildup90": 0.693,
                "big_chances_created90": 0.0,
                "tackles90": 1.187,
                "interceptions90": 1.499,
                "clearances90": 0.0,
                "goals_prevented90": 0.0
              },
              "outstanding": {
                "attacking": false,
                "creative": true,
                "defensive": false
              }
            },
            {
              "player": "Leandro Trossard",
              "fpl_position": "FWD",
              "scores": {
                "attacking": 0.437,
                "creative": 0.417,
                "defensive": 0.165
              },
              "traits": {
                "xg90": 0.25,
                "npxg90": 0.303,
                "goals90": 0.275,
                "shots90": 2.456,
                "xa90": 0.152,
                "key_passes90": 1.529,
                "xg_buildup90": 0.234,
                "big_chances_created90": 0.408,
                "tackles90": 1.151,
                "interceptions90": 0.36,
                "clearances90": 0.56,
                "goals_prevented90": 0.0
              },
              "outstanding": {
                "attacking": false,
                "creative": true,
                "defensive": false
              }
            },
            {
              "player": "Jordan Pickford",
              "fpl_position": "GK",
              "scores": {
                "attacking": 0.0,
                "creative": 0.054,
                "defensive": 0.607
              },
              "traits": {
                "xg90": 0.0,
                "npxg90": 0.0,
                "goals90": 0.0,
                "shots90": 0.0,
                "xa90": 0.006,
                "key_passes90": 0.053,
                "xg_buildup90": 0.089,
                "big_chances_created90": 0.026,
                "tackles90": 0.039,
                "interceptions90": 0.013,
                "clearances90": 1.368,
                "goals_prevented90": 0.117
              },
              "outstanding": {
                "attacking": false,
                "creative": false,
                "defensive": true
              }
            }
          ],
          "boosts": {
            "attack": 0.0,
            "creation": 0.0107,
            "defence": 0.0182,
            "total_applied_pct": 0.0289
          },
          "contributed": true,
          "summary": "3 on bench; 3 with standout quality (+2.9% squad depth boost).",
          "team": "Chintu"
        }
      }
    },
    "bench_impact": {
      "home": {
        "bench_count": 3,
        "bench_players": [
          "Declan Rice",
          "Pau Cubarsí",
          "Manuel Locatelli"
        ],
        "starting_xi": [
          "Mike Maignan",
          "Josip Stanišić",
          "Edmond Tapsoba",
          "Marc Cucurella",
          "Dayot Upamecano",
          "João Palhinha",
          "Enzo Fernández",
          "Luis Díaz",
          "Cole Palmer",
          "Gonzalo Higuaín",
          "Matheus Cunha"
        ],
        "full_squad_size": 14,
        "players": [
          {
            "player": "Declan Rice",
            "fpl_position": "MID",
            "scores": {
              "attacking": 0.195,
              "creative": 0.545,
              "defensive": 0.352
            },
            "traits": {
              "xg90": 0.102,
              "npxg90": 0.111,
              "goals90": 0.122,
              "shots90": 1.343,
              "xa90": 0.19,
              "key_passes90": 1.898,
              "xg_buildup90": 0.351,
              "big_chances_created90": 0.501,
              "tackles90": 1.858,
              "interceptions90": 0.934,
              "clearances90": 1.927,
              "goals_prevented90": 0.0
            },
            "outstanding": {
              "attacking": false,
              "creative": false,
              "defensive": false
            }
          },
          {
            "player": "Pau Cubarsí",
            "fpl_position": "DEF",
            "scores": {
              "attacking": 0.039,
              "creative": 0.302,
              "defensive": 0.366
            },
            "traits": {
              "xg90": 0.023,
              "npxg90": 0.025,
              "goals90": 0.017,
              "shots90": 0.304,
              "xa90": 0.028,
              "key_passes90": 0.238,
              "xg_buildup90": 0.604,
              "big_chances_created90": 0.068,
              "tackles90": 1.282,
              "interceptions90": 0.773,
              "clearances90": 3.92,
              "goals_prevented90": 0.0
            },
            "outstanding": {
              "attacking": false,
              "creative": true,
              "defensive": false
            }
          },
          {
            "player": "Manuel Locatelli",
            "fpl_position": "MID",
            "scores": {
              "attacking": 0.114,
              "creative": 0.424,
              "defensive": 0.437
            },
            "traits": {
              "xg90": 0.071,
              "npxg90": 0.04,
              "goals90": 0.047,
              "shots90": 1.085,
              "xa90": 0.119,
              "key_passes90": 1.164,
              "xg_buildup90": 0.472,
              "big_chances_created90": 0.138,
              "tackles90": 2.669,
              "interceptions90": 0.949,
              "clearances90": 2.264,
              "goals_prevented90": 0.0
            },
            "outstanding": {
              "attacking": false,
              "creative": true,
              "defensive": true
            }
          }
        ],
        "boosts": {
          "attack": 0.0,
          "creation": 0.0109,
          "defence": 0.0131,
          "total_applied_pct": 0.024
        },
        "contributed": true,
        "summary": "3 on bench; 2 with standout quality (+2.4% squad depth boost).",
        "team": "Anindo"
      },
      "away": {
        "bench_count": 3,
        "bench_players": [
          "Fernandinho",
          "Leandro Trossard",
          "Jordan Pickford"
        ],
        "starting_xi": [
          "Yassine Bounou",
          "Djed Spence",
          "Sergio Ramos",
          "Maxence Lacroix",
          "Malick Thiaw",
          "Adam Wharton",
          "Nicolò Barella",
          "Bruno Fernandes",
          "Mason Greenwood",
          "Erling Haaland",
          "Jérémy Doku"
        ],
        "full_squad_size": 14,
        "players": [
          {
            "player": "Fernandinho",
            "fpl_position": "MID",
            "scores": {
              "attacking": 0.2,
              "creative": 0.295,
              "defensive": 0.282
            },
            "traits": {
              "xg90": 0.077,
              "npxg90": 0.077,
              "goals90": 0.16,
              "shots90": 1.5,
              "xa90": 0.089,
              "key_passes90": 0.0,
              "xg_buildup90": 0.693,
              "big_chances_created90": 0.0,
              "tackles90": 1.187,
              "interceptions90": 1.499,
              "clearances90": 0.0,
              "goals_prevented90": 0.0
            },
            "outstanding": {
              "attacking": false,
              "creative": true,
              "defensive": false
            }
          },
          {
            "player": "Leandro Trossard",
            "fpl_position": "FWD",
            "scores": {
              "attacking": 0.437,
              "creative": 0.417,
              "defensive": 0.165
            },
            "traits": {
              "xg90": 0.25,
              "npxg90": 0.303,
              "goals90": 0.275,
              "shots90": 2.456,
              "xa90": 0.152,
              "key_passes90": 1.529,
              "xg_buildup90": 0.234,
              "big_chances_created90": 0.408,
              "tackles90": 1.151,
              "interceptions90": 0.36,
              "clearances90": 0.56,
              "goals_prevented90": 0.0
            },
            "outstanding": {
              "attacking": false,
              "creative": true,
              "defensive": false
            }
          },
          {
            "player": "Jordan Pickford",
            "fpl_position": "GK",
            "scores": {
              "attacking": 0.0,
              "creative": 0.054,
              "defensive": 0.607
            },
            "traits": {
              "xg90": 0.0,
              "npxg90": 0.0,
              "goals90": 0.0,
              "shots90": 0.0,
              "xa90": 0.006,
              "key_passes90": 0.053,
              "xg_buildup90": 0.089,
              "big_chances_created90": 0.026,
              "tackles90": 0.039,
              "interceptions90": 0.013,
              "clearances90": 1.368,
              "goals_prevented90": 0.117
            },
            "outstanding": {
              "attacking": false,
              "creative": false,
              "defensive": true
            }
          }
        ],
        "boosts": {
          "attack": 0.0,
          "creation": 0.0107,
          "defence": 0.0182,
          "total_applied_pct": 0.0289
        },
        "contributed": true,
        "summary": "3 on bench; 3 with standout quality (+2.9% squad depth boost).",
        "team": "Chintu"
      }
    },
    "sample_match": {
      "scoreline": "1-1",
      "home": {
        "team": "Anindo",
        "goals": 1,
        "xg": 2.25,
        "scorers": [
          {
            "minute": 26,
            "scorer": "Gonzalo Higuaín",
            "assister": "Luis Díaz"
          }
        ]
      },
      "away": {
        "team": "Chintu",
        "goals": 1,
        "xg": 1.96,
        "scorers": [
          {
            "minute": 83,
            "scorer": "Erling Haaland",
            "assister": null
          }
        ]
      },
      "winner": null
    },
    "season_overrides": {
      "team_a": {},
      "team_b": {}
    },
    "analysis": {
      "favorite": "Anindo",
      "favorite_side": "home",
      "margin": "slight",
      "summary": "Anindo is favoured (42.2% win vs 37.2% for Chintu, 20.6% draw). Expected goals: Anindo 2.25 – 1.96 Chintu.",
      "expected_xg": {
        "home": 2.25,
        "away": 1.96,
        "edge_side": "home",
        "delta": 0.29
      },
      "outcomes": {
        "home_win_pct": 42.2,
        "draw_pct": 20.6,
        "away_win_pct": 37.2
      },
      "key_factors": [
        {
          "factor": "Goalkeeper",
          "edge": "home",
          "home": 0.685,
          "away": 0.334,
          "delta": -0.351,
          "impact": 0.5265,
          "explanation": "Anindo has the stronger keeper (0.69 vs 0.33), shifting expected goals against."
        },
        {
          "factor": "Finishing quality",
          "edge": "home",
          "home": 0.82,
          "away": 0.724,
          "delta": -0.096,
          "impact": 0.1344,
          "explanation": "Anindo converts chances better (finishing 0.82 vs 0.72)."
        },
        {
          "factor": "Possession control",
          "edge": "home",
          "home": 0.701,
          "away": 0.509,
          "delta": -0.192,
          "impact": 0.1344,
          "explanation": "Anindo controls the ball better (0.70 vs 0.51)."
        },
        {
          "factor": "Transition risk",
          "edge": "away",
          "home": 0.242,
          "away": 0.151,
          "delta": -0.091,
          "impact": 0.10010000000000001,
          "explanation": "Chintu is more exposed on the counter (transition risk 0.24 vs 0.15 — lower is safer)."
        },
        {
          "factor": "Midfield shield",
          "edge": null,
          "home": 0.129,
          "away": 0.119,
          "delta": -0.01,
          "impact": 0.009000000000000001,
          "explanation": "even shields the defence better (mid-def 0.13 vs 0.12)."
        },
        {
          "factor": "Formation fit",
          "edge": null,
          "home": 0.754,
          "away": 0.745,
          "delta": -0.009,
          "impact": 0.0072,
          "explanation": "even fits the chosen shape better (avg fit 0.75 vs 0.74)."
        }
      ],
      "head_to_head": {
        "finishing": {
          "home": 0.82,
          "away": 0.724,
          "edge": "home"
        },
        "chance_creation": {
          "home": 1.0,
          "away": 1.0,
          "edge": null
        },
        "goalkeeper": {
          "home": 0.685,
          "away": 0.334,
          "edge": "home"
        },
        "defence": {
          "home": 0.192,
          "away": 0.187,
          "edge": null
        },
        "midfield_defence": {
          "home": 0.129,
          "away": 0.119,
          "edge": null
        },
        "transition_risk": {
          "home": 0.242,
          "away": 0.151,
          "edge": "away"
        },
        "possession": {
          "home": 0.701,
          "away": 0.509,
          "edge": "home"
        },
        "formation_fit": {
          "home": 0.754,
          "away": 0.745,
          "edge": null
        }
      },
      "mechanics_summary": {
        "home_attacks_vs_away_defence": 0.844,
        "away_attacks_vs_home_defence": 0.795,
        "midfield_battle": {
          "home_multiplier": 1.001,
          "away_multiplier": 0.999
        }
      },
      "sections": [
        {
          "title": "Verdict",
          "paragraphs": [
            "Anindo is favoured (42.2% win vs 37.2% for Chintu, 20.6% draw). Expected goals: Anindo 2.25 – 1.96 Chintu."
          ],
          "bullets": [
            "Anindo has the stronger keeper (0.69 vs 0.33), shifting expected goals against.",
            "Anindo converts chances better (finishing 0.82 vs 0.72).",
            "Anindo controls the ball better (0.70 vs 0.51)."
          ]
        },
        {
          "title": "Squad depth (bench impact)",
          "paragraphs": [
            "Non-starters with elite per-90 traits add a small squad-depth multiplier to unit ratings (capped at ~5% total; bench cannot dominate outcomes).",
            "Anindo: 3 on bench; 2 with standout quality (+2.4% squad depth boost). Standouts: Pau Cubarsí, Manuel Locatelli. Boosts — attack +0.0%, creation +1.1%, defence +1.3%.",
            "Chintu: 3 on bench; 3 with standout quality (+2.9% squad depth boost). Standouts: Fernandinho, Leandro Trossard, Jordan Pickford. Boosts — attack +0.0%, creation +1.1%, defence +1.8%."
          ],
          "bullets": []
        },
        {
          "title": "Expected goals pipeline",
          "paragraphs": [
            "The engine splits attack into finishing and chance-creation channels, then applies opponent suppression and midfield battle modifiers.",
            "Anindo raw attack xG: 2.34 finishing + 0.37 creation = 2.71 before suppression. When Chintu defends, suppression factor is 0.795 (DEF 0.19, mid-def 0.12, GK 0.33, transition risk 0.15).",
            "Chintu raw attack xG: 2.17 + 0.37 = 2.54. Anindo suppression when defending: 0.844 (transition risk 0.24).",
            "Midfield battle multipliers: Anindo ×1.001, Chintu ×0.999. Net xG edge: Anindo by 0.29."
          ],
          "bullets": []
        },
        {
          "title": "Defensive structure & transitions",
          "paragraphs": [
            "Anindo xGA suppression: 0.795 (base without transition penalty: 0.782). Chintu: 0.844 (base 0.837).",
            "Anindo fullbacks: Josip Stanišić (RB, exposure 0.30), Dayot Upamecano (LB, exposure 0.18). Team transition risk 0.242 — high attacking fullbacks increase counter vulnerability when midfield cover is thin.",
            "Chintu fullbacks: Djed Spence (RB, exposure 0.16), Malick Thiaw (LB, exposure 0.08). Team transition risk 0.151 — high attacking fullbacks increase counter vulnerability when midfield cover is thin."
          ],
          "bullets": []
        },
        {
          "title": "Formation & squad fit",
          "paragraphs": [
            "Anindo (4-3-3): average formation fit 0.75. Chance creation index 0.46, possession 0.70.",
            "Chintu (4-3-3): average formation fit 0.74. Chance creation index 0.47, possession 0.51."
          ],
          "bullets": []
        },
        {
          "title": "Monte Carlo interpretation",
          "paragraphs": [
            "Across 500 neutral-venue runs, average scoreline tendency is 2.09–1.92. Both teams score 74.2% of the time; over 2.5 goals 76.6%.",
            "Most common scoreline: 2-2 (7.6%)."
          ],
          "bullets": [
            "Trophy boost: Anindo ×1.020, Chintu ×1.006 (applied in simulation units)."
          ]
        }
      ]
    },
    "squad_analysis": {
      "home": {
        "name": "Anindo",
        "formation": "4-3-3",
        "summary": "Anindo: Strong attack (0.90).; Strong finishing (0.82).",
        "strengths": [
          "Strong attack (0.90).",
          "Strong finishing (0.82).",
          "Strong chance creation (1.00).",
          "Strong goalkeeper (0.69).",
          "Strong transition safety (0.24).",
          "Players suit the 4-3-3 shape (avg fit 0.75)."
        ],
        "weaknesses": [
          "Thin midfield (0.25).",
          "Thin defence (0.19).",
          "Thin midfield shield (0.13)."
        ],
        "sections": [
          {
            "title": "Attack",
            "bullets": [
              "Attacking effectiveness index 0.79.",
              "Chance creation index 0.46; forwards avg xG/90 0.51.",
              "Raw xG split: finishing 2.34 + creation 0.37."
            ]
          },
          {
            "title": "Midfield",
            "bullets": [
              "Midfield rating 0.25; possession control 0.70.",
              "Pass completion avg 85.2%.",
              "Pressing intensity 0.49."
            ]
          },
          {
            "title": "Defence",
            "bullets": [
              "Back-line defence 0.19; midfield shield 0.13.",
              "xGA suppression 0.795; aerial defence 0.55.",
              "Transition risk 0.24 (lower is safer).",
              "Wide defenders: Josip Stanišić (RB), Dayot Upamecano (LB)."
            ]
          },
          {
            "title": "Formation fit",
            "bullets": [
              "Average formation fit 0.75 in 4-3-3.",
              "No major formation-fit concerns in the starting XI."
            ]
          },
          {
            "title": "Squad depth",
            "bullets": [
              "3 on bench; 2 with standout quality (+2.4% squad depth boost).",
              "Depth boosts: attack +0.0%, creation +1.1%, defence +1.3%.",
              "Standout bench options: Pau Cubarsí, Manuel Locatelli."
            ]
          }
        ],
        "units": {
          "attack": 0.899,
          "finishing": 0.82,
          "chance_creation": 1.0,
          "midfield": 0.249,
          "defence": 0.192,
          "midfield_defence": 0.129,
          "transition_risk": 0.242,
          "goalkeeper": 0.685,
          "overall": 0.489,
          "gk_confidence": 0.953,
          "gk_is_backup": 0.0
        }
      },
      "away": {
        "name": "Chintu",
        "formation": "4-3-3",
        "summary": "Chintu: Strong attack (0.84).; Strong finishing (0.72).",
        "strengths": [
          "Strong attack (0.84).",
          "Strong finishing (0.72).",
          "Strong chance creation (1.00).",
          "Strong transition safety (0.15).",
          "Players suit the 4-3-3 shape (avg fit 0.74).",
          "Useful bench depth (Fernandinho, Leandro Trossard, Jordan Pickford)."
        ],
        "weaknesses": [
          "Thin midfield (0.24).",
          "Thin defence (0.19).",
          "Thin midfield shield (0.12).",
          "Thin goalkeeper (0.33)."
        ],
        "sections": [
          {
            "title": "Attack",
            "bullets": [
              "Attacking effectiveness index 0.81.",
              "Chance creation index 0.47; forwards avg xG/90 0.64.",
              "Raw xG split: finishing 2.17 + creation 0.37."
            ]
          },
          {
            "title": "Midfield",
            "bullets": [
              "Midfield rating 0.24; possession control 0.51.",
              "Pass completion avg 74.9%.",
              "Pressing intensity 0.46."
            ]
          },
          {
            "title": "Defence",
            "bullets": [
              "Back-line defence 0.19; midfield shield 0.12.",
              "xGA suppression 0.844; aerial defence 0.63.",
              "Transition risk 0.15 (lower is safer).",
              "Wide defenders: Djed Spence (RB), Malick Thiaw (LB)."
            ]
          },
          {
            "title": "Formation fit",
            "bullets": [
              "Average formation fit 0.74 in 4-3-3.",
              "No major formation-fit concerns in the starting XI."
            ]
          },
          {
            "title": "Squad depth",
            "bullets": [
              "3 on bench; 3 with standout quality (+2.9% squad depth boost).",
              "Depth boosts: attack +0.0%, creation +1.1%, defence +1.8%.",
              "Standout bench options: Fernandinho, Leandro Trossard, Jordan Pickford."
            ]
          }
        ],
        "units": {
          "attack": 0.845,
          "finishing": 0.724,
          "chance_creation": 1.0,
          "midfield": 0.243,
          "defence": 0.187,
          "midfield_defence": 0.119,
          "transition_risk": 0.151,
          "goalkeeper": 0.334,
          "overall": 0.425,
          "gk_confidence": 0.82,
          "gk_is_backup": 0.0
        }
      }
    }
  }
}